rich_json_logs/__init__.py
rich_json_logs/highlighter.py
rich_json_logs/log.py
rich_json_logs-0.2.0.dist-info/WHEEL
rich_json_logs-0.2.0.dist-info/METADATA
rich_json_logs-0.2.0.dist-info/RECORD
