Metadata-Version: 2.1
Name: rich-json-logs
Version: 0.2.0
Summary: 
Author: gsantoro
Author-email: giuseppe.santoro@gmail.com
Requires-Python: >=3.10.5,<4.0.0
Classifier: Programming Language :: Python :: 3
Classifier: Programming Language :: Python :: 3.11
Requires-Dist: click (>=8.1.3,<9.0.0)
Requires-Dist: jsonpath-ng (>=1.5.3,<2.0.0)
Requires-Dist: rich (>=12.6.0,<13.0.0)
